{
  "updated": "2026-04-07T06:47:03Z",
  "trends": [
    {
      "topic": "LKs 谁是理财王",
      "source": "bilibili",
      "heat": 0
    },
    {
      "topic": "Faker称已准备好迎战马斯克AI",
      "source": "bilibili",
      "heat": 0
    },
    {
      "topic": "郑丽文率团抵达上海",
      "source": "bilibili",
      "heat": 0
    },
    {
      "topic": "曝GPT6本月发布",
      "source": "bilibili",
      "heat": 0
    },
    {
      "topic": "中国捏脸史",
      "source": "bilibili",
      "heat": 0
    },
    {
      "topic": "7人非法薅羊毛12万元被抓",
      "source": "bilibili",
      "heat": 0
    },
    {
      "topic": "karrigan谈FaZe困境",
      "source": "bilibili",
      "heat": 0
    },
    {
      "topic": "歌剧老师锐评浪姐舞台",
      "source": "bilibili",
      "heat": 0
    },
    {
      "topic": "马刺战胜76人收获单赛季60胜",
      "source": "bilibili",
      "heat": 0
    },
    {
      "topic": "雪山救狐但内娱版",
      "source": "bilibili",
      "heat": 0
    },
    {
      "topic": "原神莉奈娅角色预告",
      "source": "bilibili",
      "heat": 0
    },
    {
      "topic": "李大霄谈熊猫债发行规模大增",
      "source": "bilibili",
      "heat": 0
    },
    {
      "topic": "光伏产品出口退税为何取消",
      "source": "bilibili",
      "heat": 0
    },
    {
      "topic": "三角洲S9赛季测试服优化汇总",
      "source": "bilibili",
      "heat": 0
    },
    {
      "topic": "三角洲S9赛季全新子弹解析",
      "source": "bilibili",
      "heat": 0
    },
    {
      "topic": "UP主揭秘高中生摆摊创业套路",
      "source": "bilibili",
      "heat": 0
    },
    {
      "topic": "鲁豫文淇聊恋爱观",
      "source": "bilibili",
      "heat": 0
    },
    {
      "topic": "怎么看球童拿走多纳鲁马小纸条",
      "source": "bilibili",
      "heat": 0
    },
    {
      "topic": "美军飞行员营救行动复盘",
      "source": "bilibili",
      "heat": 0
    },
    {
      "topic": "伊朗发布被击落美军机画面",
      "source": "bilibili",
      "heat": 0
    }
  ]
}