{
  "updated": "2026-05-08T22:38:40Z",
  "trends": [
    {
      "topic": "世界杯转播权到底有多贵",
      "source": "bilibili",
      "heat": 0
    },
    {
      "topic": "JDG BLG",
      "source": "bilibili",
      "heat": 0
    },
    {
      "topic": "解析安理会朝鲜核问题会议",
      "source": "bilibili",
      "heat": 0
    },
    {
      "topic": "无锡TCG 杭州LGD.NBW",
      "source": "bilibili",
      "heat": 0
    },
    {
      "topic": "00后新人大战",
      "source": "bilibili",
      "heat": 0
    },
    {
      "topic": "Faker柳智敏跨次元联动",
      "source": "bilibili",
      "heat": 0
    },
    {
      "topic": "EDG 2-0 XLG数据雷达图",
      "source": "bilibili",
      "heat": 0
    },
    {
      "topic": "外星小偷里贝",
      "source": "bilibili",
      "heat": 0
    },
    {
      "topic": "记录星空卫视停播时刻",
      "source": "bilibili",
      "heat": 0
    },
    {
      "topic": "复盘曾经的王King是怎么火起来的",
      "source": "bilibili",
      "heat": 0
    },
    {
      "topic": "XLG EDG",
      "source": "bilibili",
      "heat": 0
    },
    {
      "topic": "AG DRG",
      "source": "bilibili",
      "heat": 0
    },
    {
      "topic": "外交部证实遇袭油轮上有中国籍船员",
      "source": "bilibili",
      "heat": 0
    },
    {
      "topic": "天舟十号将于近日择机发射",
      "source": "bilibili",
      "heat": 0
    },
    {
      "topic": "如何看待油股同涨",
      "source": "bilibili",
      "heat": 0
    },
    {
      "topic": "皇马更衣室怎么了",
      "source": "bilibili",
      "heat": 0
    },
    {
      "topic": "中国超大型清洁能源船获重大突破",
      "source": "bilibili",
      "heat": 0
    },
    {
      "topic": "成为王的代价是什么",
      "source": "bilibili",
      "heat": 0
    },
    {
      "topic": "King全新单曲 王的归来",
      "source": "bilibili",
      "heat": 0
    },
    {
      "topic": "黑袍5第6集是如何反转的",
      "source": "bilibili",
      "heat": 0
    }
  ]
}