{
  "updated": "2026-04-11T21:15:45Z",
  "trends": [
    {
      "topic": "KSG 4-0 重庆狼队赛后数据",
      "source": "bilibili",
      "heat": 0
    },
    {
      "topic": "宇树再次刷新世界纪录",
      "source": "bilibili",
      "heat": 0
    },
    {
      "topic": "隐秘的欧洲黑帮之国",
      "source": "bilibili",
      "heat": 0
    },
    {
      "topic": "四川舰福建舰能否联合运用",
      "source": "bilibili",
      "heat": 0
    },
    {
      "topic": "EDG DRG",
      "source": "bilibili",
      "heat": 0
    },
    {
      "topic": "阿森纳1-2伯恩茅斯",
      "source": "bilibili",
      "heat": 0
    },
    {
      "topic": "JDG TES",
      "source": "bilibili",
      "heat": 0
    },
    {
      "topic": "常州3-0南通",
      "source": "bilibili",
      "heat": 0
    },
    {
      "topic": "有一名浪人前来买瓜",
      "source": "bilibili",
      "heat": 0
    },
    {
      "topic": "80000字解读孙俪悬疑新剧",
      "source": "bilibili",
      "heat": 0
    },
    {
      "topic": "浪姐一公小考有多少槽点",
      "source": "bilibili",
      "heat": 0
    },
    {
      "topic": "IG WE",
      "source": "bilibili",
      "heat": 0
    },
    {
      "topic": "美载人飞船结束绕月之旅",
      "source": "bilibili",
      "heat": 0
    },
    {
      "topic": "警方通报全红婵遭网暴事件",
      "source": "bilibili",
      "heat": 0
    },
    {
      "topic": "李大霄解读美股单周表现",
      "source": "bilibili",
      "heat": 0
    },
    {
      "topic": "KSG流浪获KPL春季赛FMVP",
      "source": "bilibili",
      "heat": 0
    },
    {
      "topic": "一半一半练习室直拍",
      "source": "bilibili",
      "heat": 0
    },
    {
      "topic": "2026苏超前瞻",
      "source": "bilibili",
      "heat": 0
    },
    {
      "topic": "浪姐舞台一半一半对耳朵很好",
      "source": "bilibili",
      "heat": 0
    },
    {
      "topic": "AG TYL",
      "source": "bilibili",
      "heat": 0
    }
  ]
}